fluidtop/__init__.py
fluidtop/fluidtop.py
fluidtop/parsers.py
fluidtop/utils.py
fluidtop-0.1.5.dist-info/METADATA
fluidtop-0.1.5.dist-info/WHEEL
fluidtop-0.1.5.dist-info/entry_points.txt
fluidtop-0.1.5.dist-info/licenses/LICENSE
fluidtop-0.1.5.dist-info/RECORD
