Metadata-Version: 2.4
Name: fluidtop
Version: 0.1.5
Summary: Real-time macOS hardware performance monitoring for Apple Silicon (M1/M2/M3/M4) with AI workload focus - enhanced asitop alternative
Project-URL: Homepage, https://github.com/FluidInference/fluidtop
Project-URL: Repository, https://github.com/FluidInference/fluidtop
Project-URL: Issues, https://github.com/FluidInference/fluidtop/issues
Project-URL: Documentation, https://github.com/FluidInference/fluidtop#readme
Project-URL: Changelog, https://github.com/FluidInference/fluidtop/releases
Author-email: Fluid Inference <dev@fluidinference.com>
License-Expression: MIT
License-File: LICENSE
Keywords: ai,ane,apple-silicon,artificial-intelligence,asitop,cli,command-line,cpu,fluidtop,gpu,hardware,htop,m1,m2,m3,m4,machine-learning,macos,memory,ml,monitoring,neural-engine,nvtop,performance,powermetrics,realtime,system-monitor,terminal,workload
Classifier: Development Status :: 4 - Beta
Classifier: Environment :: Console
Classifier: Intended Audience :: Developers
Classifier: Intended Audience :: Science/Research
Classifier: Intended Audience :: System Administrators
Classifier: License :: OSI Approved :: MIT License
Classifier: Operating System :: MacOS
Classifier: Operating System :: MacOS :: MacOS X
Classifier: Programming Language :: Python :: 3
Classifier: Programming Language :: Python :: 3.10
Classifier: Programming Language :: Python :: 3.11
Classifier: Programming Language :: Python :: 3.12
Classifier: Programming Language :: Python :: 3.13
Classifier: Topic :: Scientific/Engineering :: Artificial Intelligence
Classifier: Topic :: Software Development :: Debuggers
Classifier: Topic :: System :: Hardware
Classifier: Topic :: System :: Monitoring
Classifier: Topic :: System :: Systems Administration
Classifier: Topic :: Utilities
Requires-Python: >=3.10
Requires-Dist: click>=8.2.0
Requires-Dist: psutil>=7.0.0
Requires-Dist: textual-plotext>=1.0.0
Requires-Dist: textual>=3.0.0
